Preprocess/FeatureEngineering.py
Preprocess/__init__.py
featureeng_arun8nov-0.0.2.dist-info/licenses/LICENSE
featureeng_arun8nov-0.0.2.dist-info/METADATA
featureeng_arun8nov-0.0.2.dist-info/WHEEL
featureeng_arun8nov-0.0.2.dist-info/top_level.txt
featureeng_arun8nov-0.0.2.dist-info/RECORD
