Metadata-Version: 2.4
Name: FeatureEng_arun8nov
Version: 0.0.2
Summary: A collection of feature engineering methods for preprocessing datasets.
Home-page: https://github.com/arun8nov/FeatureEng
Author: Arunprakash
Author-email: arunbabuprakash@gmail.com
Classifier: Programming Language :: Python :: 3
Classifier: License :: OSI Approved :: MIT License
Classifier: Operating System :: OS Independent
Requires-Python: >=3.6
License-File: LICENSE
Requires-Dist: pandas
Requires-Dist: numpy
Dynamic: author
Dynamic: author-email
Dynamic: classifier
Dynamic: description
Dynamic: description-content-type
Dynamic: home-page
Dynamic: license-file
Dynamic: requires-dist
Dynamic: requires-python
Dynamic: summary
